hopcolony/__about__.py
hopcolony/__init__.py
hopcolony/__main__.py
hopcolony/auth/__init__.py
hopcolony/auth/auth_token.py
hopcolony/auth/auth_user.py
hopcolony/docs/__init__.py
hopcolony/docs/docs_document.py
hopcolony/docs/docs_index.py
hopcolony/drive/__init__.py
hopcolony/drive/drive_bucket.py
hopcolony/drive/drive_object.py
hopcolony/drive/drive_signer.py
hopcolony/hopctl/__init__.py
hopcolony/hopctl/config.py
hopcolony/hopctl/describe.py
hopcolony/hopctl/get.py
hopcolony/hopctl/jobs.py
hopcolony/jobs/__init__.py
hopcolony/jobs/jobs.py
hopcolony/jobs/jobs_pipelines.py
hopcolony/jobs/utils.py
hopcolony/topics/__init__.py
hopcolony/topics/exchange.py
hopcolony/topics/queue.py
tests/__init__.py
tests/config.py
tests/test_auth.py
tests/test_docs.py
tests/test_drive.py
tests/test_init.py
tests/test_topics.py
hopcolony-0.1.6.dist-info/LICENSE
hopcolony-0.1.6.dist-info/METADATA
hopcolony-0.1.6.dist-info/WHEEL
hopcolony-0.1.6.dist-info/entry_points.txt
hopcolony-0.1.6.dist-info/top_level.txt
hopcolony-0.1.6.dist-info/RECORD
